netchat/__init__.py
netchat/netchat.py
netchat-1.0.3.dist-info/LICENSE
netchat-1.0.3.dist-info/METADATA
netchat-1.0.3.dist-info/WHEEL
netchat-1.0.3.dist-info/entry_points.txt
netchat-1.0.3.dist-info/top_level.txt
netchat-1.0.3.dist-info/RECORD
