Metadata-Version: 2.1
Name: netchat
Version: 1.0.3
Summary: netchat connects to a listening tcp port, waits for text and sends responses
Home-page: UNKNOWN
License: MIT
Platform: UNKNOWN
Requires-Python: >=3.8
License-File: LICENSE
Requires-Dist: click
Requires-Dist: pexpect
Provides-Extra: dev
Requires-Dist: bumpversion ; extra == 'dev'
Requires-Dist: twine ; extra == 'dev'
Requires-Dist: yapf ; extra == 'dev'
Requires-Dist: python-dotenv ; extra == 'dev'
Provides-Extra: docs
Requires-Dist: sphinx ; extra == 'docs'
Provides-Extra: test
Requires-Dist: pytest ; extra == 'test'
Requires-Dist: pytest-click ; extra == 'test'
Requires-Dist: tox ; extra == 'test'
